pltext/__init__.py
pltext/client.py
pltext-0.1.0.dist-info/METADATA
pltext-0.1.0.dist-info/WHEEL
pltext-0.1.0.dist-info/top_level.txt
pltext-0.1.0.dist-info/RECORD
