Metadata-Version: 2.4
Name: pltext
Version: 0.1.0
Summary: PLText API wrapper for Python
Author: Your Name
License: MIT
Project-URL: Homepage, https://pypi.org/project/pltext/
Project-URL: Source, https://github.com/yourusername/pltext
Keywords: pltext,api,plagiarism,wrapper
Requires-Dist: requests
Requires-Dist: python-dotenv
